prestring/__init__.py
prestring/codeobject.py
prestring/naming.py
prestring/output.py
prestring/py.typed
prestring/types.py
prestring/utils.py
prestring/go/__init__.py
prestring/go/codeobject.py
prestring/go/gofmt.py
prestring/minifs/__init__.py
prestring/minifs/_flatten.py
prestring/minifs/_glob.py
prestring/python/__init__.py
prestring/python/__main__.py
prestring/python/cli.py
prestring/python/codeobject.py
prestring/python/parse.py
prestring/python/transform.py
prestring/text/__init__.py
prestring/text/__main__.py
prestring/text/transform.py
prestring-0.9.0.dist-info/LICENSE
prestring-0.9.0.dist-info/METADATA
prestring-0.9.0.dist-info/WHEEL
prestring-0.9.0.dist-info/entry_points.txt
prestring-0.9.0.dist-info/top_level.txt
prestring-0.9.0.dist-info/RECORD
