Metadata-Version: 2.1
Name: prestring
Version: 0.9.0
Summary: source code generation library (with overuse with-syntax)
Home-page: https://github.com/podhmo/prestring
Author: podhmo
Author-email: ababjam61@gmail.com
License: UNKNOWN
Keywords: prestring,srcgen,python
Platform: UNKNOWN
Classifier: Programming Language :: Python
Classifier: Intended Audience :: Developers
Classifier: Topic :: Software Development :: Libraries :: Python Modules
Classifier: License :: OSI Approved :: MIT License
Classifier: Operating System :: OS Independent
Classifier: Programming Language :: Python :: 3
Classifier: Programming Language :: Python :: 3.6
Classifier: Programming Language :: Python :: 3.7
Classifier: Programming Language :: Python :: 3.8
Requires-Dist: typing-extensions
Provides-Extra: dev
Requires-Dist: black ; extra == 'dev'
Requires-Dist: flake8 ; extra == 'dev'
Requires-Dist: mypy ; extra == 'dev'
Provides-Extra: docs
Provides-Extra: testing
Requires-Dist: evilunit ; extra == 'testing'
